pyroved/__init__.py
pyroved/__version__.py
pyroved/models/__init__.py
pyroved/models/base.py
pyroved/models/ivae.py
pyroved/models/jivae.py
pyroved/models/ss_reg_ivae.py
pyroved/models/ssivae.py
pyroved/models/ved.py
pyroved/nets/__init__.py
pyroved/nets/conv.py
pyroved/nets/fc.py
pyroved/trainers/__init__.py
pyroved/trainers/auxsvi.py
pyroved/trainers/svi.py
pyroved/utils/__init__.py
pyroved/utils/coord.py
pyroved/utils/data.py
pyroved/utils/nn.py
pyroved/utils/prob.py
pyroved/utils/viz.py
tests/__init__.py
tests/test_conv.py
tests/test_models.py
tests/test_trainers.py
pyroved-0.3.0.dist-info/LICENSE
pyroved-0.3.0.dist-info/METADATA
pyroved-0.3.0.dist-info/WHEEL
pyroved-0.3.0.dist-info/top_level.txt
pyroved-0.3.0.dist-info/RECORD
