Metadata-Version: 2.1
Name: pyroved
Version: 0.3.0
Summary: Variational encoder-decoder models in Pyro probabilistic programming language
Home-page: https://github.com/ziatdinovmax/pyroVED/
Author: Maxim Ziatdinov
Author-email: maxim.ziatdinov@ai4microcopy.com
License: MIT license
Platform: UNKNOWN
Classifier: Programming Language :: Python
Classifier: Development Status :: 3 - Alpha
Classifier: Intended Audience :: Science/Research
Classifier: Operating System :: OS Independent
Classifier: Topic :: Scientific/Engineering
Requires-Python: >=3.6
License-File: LICENSE
Requires-Dist: pyro-ppl (>=1.6.0)
Requires-Dist: matplotlib (>=3.2)
Requires-Dist: torchvision (>=0.7.0)
